solana_inscription_py/__init__.py
solana_inscription_py/main.py
solana_inscription_py-0.1.4.dist-info/METADATA
solana_inscription_py-0.1.4.dist-info/WHEEL
solana_inscription_py-0.1.4.dist-info/top_level.txt
solana_inscription_py-0.1.4.dist-info/RECORD
