Metadata-Version: 2.1
Name: solana-inscription-py
Version: 0.1.4
Summary: Mint Solana Inscriptions
Home-page: https://github.com/cksc123/solana_inscription_py
Author: CK
Author-email: admin@example.com
License: MIT
Project-URL: Source, https://github.com/cksc123/solana_inscription_py
Platform: UNKNOWN
Classifier: License :: OSI Approved :: MIT License
Classifier: Programming Language :: Python :: 3
Classifier: Operating System :: OS Independent
Requires-Dist: solana (<=0.30.2)
